qflow/__init__.py
qflow/definitions.cpp
qflow/definitions.hpp
qflow/distance.cpp
qflow/distance.hpp
qflow/hamiltonians/__init__.py
qflow/hamiltonians/coulombharmonicoscillator.cpp
qflow/hamiltonians/coulombharmonicoscillator.hpp
qflow/hamiltonians/hamiltonian.cpp
qflow/hamiltonians/hamiltonian.hpp
qflow/hamiltonians/hardsphereharmonicoscillator.cpp
qflow/hamiltonians/hardsphereharmonicoscillator.hpp
qflow/hamiltonians/harmonicoscillator.cpp
qflow/hamiltonians/harmonicoscillator.hpp
qflow/hamiltonians/hfdhe2.cpp
qflow/hamiltonians/hfdhe2.hpp
qflow/hamiltonians/lennardjones.cpp
qflow/hamiltonians/lennardjones.hpp
qflow/hamiltonians/pyhamiltonian.cpp
qflow/mpi.py
qflow/mpiutil.cpp
qflow/mpiutil.hpp
qflow/optimizers/__init__.py
qflow/optimizers/optimizer.cpp
qflow/optimizers/optimizer.hpp
qflow/optimizers/pyoptimizer.cpp
qflow/pymain.cpp
qflow/samplers/__init__.py
qflow/samplers/boxsampler.hpp
qflow/samplers/gibbssampler.cpp
qflow/samplers/gibbssampler.hpp
qflow/samplers/heliumsampler.cpp
qflow/samplers/heliumsampler.hpp
qflow/samplers/importancesampler.cpp
qflow/samplers/importancesampler.hpp
qflow/samplers/metropolissampler.cpp
qflow/samplers/metropolissampler.hpp
qflow/samplers/pysampler.cpp
qflow/samplers/sampler.cpp
qflow/samplers/sampler.hpp
qflow/statistics.py
qflow/system.hpp
qflow/training.py
qflow/vector.hpp
qflow/wavefunctions/__init__.py
qflow/wavefunctions/fixedwavefunction.hpp
qflow/wavefunctions/hardspherewavefunction.cpp
qflow/wavefunctions/hardspherewavefunction.hpp
qflow/wavefunctions/inputsorter.cpp
qflow/wavefunctions/inputsorter.hpp
qflow/wavefunctions/jastrowmcmillian.cpp
qflow/wavefunctions/jastrowmcmillian.hpp
qflow/wavefunctions/jastroworion.cpp
qflow/wavefunctions/jastroworion.hpp
qflow/wavefunctions/jastrowpade.cpp
qflow/wavefunctions/jastrowpade.hpp
qflow/wavefunctions/nn/__init__.py
qflow/wavefunctions/nn/activations/__init__.py
qflow/wavefunctions/nn/activations/activation.cpp
qflow/wavefunctions/nn/activations/activation.hpp
qflow_vmc-0.2.0.dist-info/LICENSE
qflow_vmc-0.2.0.dist-info/WHEEL
qflow_vmc-0.2.0.dist-info/METADATA
qflow_vmc-0.2.0.dist-info/RECORD
