Metadata-Version: 2.1
Name: qflow-vmc
Version: 0.2.0
Summary: Quantum Variational Monte Carlo
Home-page: https://bsamseth.github.io/qflow
License: MIT
Author: Bendik Samseth
Author-email: b.samseth@gmail.com
Requires-Python: >=3.7,<4.0
Classifier: License :: OSI Approved :: MIT License
Classifier: Programming Language :: Python :: 3
Classifier: Programming Language :: Python :: 3.7
Classifier: Programming Language :: Python :: 3.8
Classifier: Programming Language :: Python :: 3.9
Requires-Dist: mpi4py (>=3.0.3,<4.0.0)
Project-URL: Repository, https://github.com/bsamseth/qflow
